MANIFEST.in
README.rst
setup.cfg
setup.py
py4jdbc/__init__.py
py4jdbc/ansiterm.py
py4jdbc/dbapi2.py
py4jdbc/gateway_process.py
py4jdbc/java_sql_types.py
py4jdbc/resultset.py
py4jdbc/settings.py
py4jdbc/sqla_compat.py
py4jdbc/utils.py
py4jdbc/version.py
py4jdbc.egg-info/PKG-INFO
py4jdbc.egg-info/SOURCES.txt
py4jdbc.egg-info/dependency_links.txt
py4jdbc.egg-info/not-zip-safe
py4jdbc.egg-info/requires.txt
py4jdbc.egg-info/top_level.txt
py4jdbc/exceptions/__init__.py
py4jdbc/exceptions/dbapi2.py
py4jdbc/exceptions/derby.py
py4jdbc/exceptions/postgres.py
py4jdbc/exceptions/py4j.py
py4jdbc/exceptions/sqlstate.py
py4jdbc/exceptions/vertica.py
py4jdbc/scala/LICENCE
py4jdbc/scala/build.sbt
py4jdbc/scala/project/assembly.sbt
py4jdbc/scala/src/main/scala/GatewayServer.scala