Metadata-Version: 1.1
Name: py4jdbc
Version: 0.1.6.8
Summary: py4j JDBC wrapper
Home-page: https://github.com/massmutual/py4jdbc
Author: Thom Neale
Author-email: tneale@massmutual.com
License: BSD
Keywords: jdbc,dbapi,py4j
Platform: UNKNOWN
Classifier: Development Status :: 2 - Pre-Alpha
Classifier: Intended Audience :: Developers
Classifier: Natural Language :: English
Classifier: Programming Language :: Python :: 3
Classifier: Programming Language :: Python :: 3.3
Classifier: Programming Language :: Python :: 3.4
Classifier: Programming Language :: Python :: 3.5
